ISY994_Homie4_Bridge-0.4.9.data/scripts/isy_homie_start.py
isy_homie/__init__.py
isy_homie/bridge.py
isy_homie/devices/__init__.py
isy_homie/devices/base.py
isy_homie/devices/contact.py
isy_homie/devices/controller_action.py
isy_homie/devices/dimmer.py
isy_homie/devices/fan.py
isy_homie/devices/isy_controller.py
isy_homie/devices/program.py
isy_homie/devices/scene.py
isy_homie/devices/siren.py
isy_homie/devices/switch.py
isy_homie/devices/thermostat.py
isy_homie/devices/variable.py
ISY994_Homie4_Bridge-0.4.9.dist-info/LICENSE
ISY994_Homie4_Bridge-0.4.9.dist-info/METADATA
ISY994_Homie4_Bridge-0.4.9.dist-info/WHEEL
ISY994_Homie4_Bridge-0.4.9.dist-info/top_level.txt
ISY994_Homie4_Bridge-0.4.9.dist-info/RECORD
