Metadata-Version: 2.1
Name: ISY994-Homie4-Bridge
Version: 0.4.9
Summary: Homie 4 for Universal Devices ISY994
Home-page: https://github.com/mjcumming/ISY-Homie-Bridge
Author: Michael Cumming
Author-email: mike@4831.com
License: UNKNOWN
Keywords: HOMIE,MQTT,ISY994,ISY,Universal Devices,zWave,Insteon
Platform: UNKNOWN
Classifier: Development Status :: 5 - Production/Stable
Classifier: License :: OSI Approved :: MIT License
Classifier: Operating System :: OS Independent
Requires-Python: >=3
License-File: LICENSE
Requires-Dist: Homie4 (>=0.3.9)
Requires-Dist: ISY994v5 (>=0.9.7)
Requires-Dist: pyyaml
